{
  "meta": {
    "game_type": "Cash",
    "table_size": "6max",
    "stack_depth": "100bb",
    "label": "NL10 GTO Wizard — live parse"
  },
  "config": {
    "positions": [
      "UTG",
      "MP",
      "CO",
      "BTN",
      "SB",
      "BB"
    ],
    "rfi_positions": [
      "UTG",
      "MP",
      "CO",
      "BTN",
      "SB"
    ],
    "vs_rfi_options": {
      "MP": [
        "UTG"
      ],
      "CO": [
        "UTG",
        "MP"
      ],
      "BTN": [
        "UTG",
        "MP",
        "CO"
      ],
      "SB": [
        "UTG",
        "MP",
        "CO",
        "BTN"
      ],
      "BB": [
        "UTG",
        "MP",
        "CO",
        "BTN",
        "SB"
      ]
    },
    "vs_3bet_options": {
      "UTG": [
        "MP",
        "CO",
        "BTN",
        "SB",
        "BB"
      ],
      "MP": [
        "CO",
        "BTN",
        "SB",
        "BB"
      ],
      "CO": [
        "BTN",
        "SB",
        "BB"
      ],
      "BTN": [
        "SB",
        "BB"
      ],
      "SB": [
        "BB"
      ]
    },
    "vs_4bet_options": {
      "MP": [
        "UTG"
      ],
      "CO": [
        "UTG",
        "MP"
      ],
      "BTN": [
        "UTG",
        "MP",
        "CO"
      ],
      "SB": [
        "UTG",
        "MP",
        "CO",
        "BTN"
      ],
      "BB": [
        "UTG",
        "MP",
        "CO",
        "BTN",
        "SB"
      ]
    }
  },
  "spots": {
    "vs_3bet": {
      "MP": {
        "vs_CO": {
          "33": {
            "call": 1
          },
          "44": {
            "call": 1
          },
          "55": {
            "call": 0.56
          },
          "66": {
            "call": 0.21
          },
          "77": {
            "call": 0.3
          },
          "88": {
            "call": 0.37
          },
          "99": {
            "call": 0.35
          },
          "AA": {
            "4bet": 1
          },
          "AKs": {
            "4bet": 1
          },
          "AQs": {
            "call": 1
          },
          "AJs": {
            "4bet": 0.68,
            "call": 0.32
          },
          "ATs": {
            "4bet": 0.34,
            "call": 0.22
          },
          "A9s": {
            "4bet": 0.09
          },
          "A8s": {
            "4bet": 0.23
          },
          "A7s": {
            "4bet": 0.18
          },
          "A6s": {
            "4bet": 0.04
          },
          "A5s": {
            "4bet": 0.41,
            "call": 0.1
          },
          "A4s": {
            "4bet": 0.07
          },
          "A3s": {
            "4bet": 0.02
          },
          "AKo": {
            "4bet": 0.74,
            "call": 0.26
          },
          "KK": {
            "4bet": 1
          },
          "KQs": {
            "4bet": 0.59,
            "call": 0.4
          },
          "KJs": {
            "4bet": 0.97,
            "call": 0.03
          },
          "KTs": {
            "4bet": 1
          },
          "K9s": {
            "4bet": 0.45
          },
          "K8s": {
            "4bet": 0.2
          },
          "K7s": {
            "4bet": 0.19
          },
          "K6s": {
            "4bet": 0.35
          },
          "AQo": {
            "4bet": 0.78
          },
          "QQ": {
            "4bet": 0.95,
            "call": 0.05
          },
          "QJs": {
            "call": 0.01
          },
          "JJ": {
            "4bet": 0.31,
            "call": 0.69
          },
          "JTs": {
            "call": 0.24
          },
          "TT": {
            "call": 0.4
          },
          "T9s": {
            "call": 0.34
          },
          "98s": {
            "call": 0.81
          },
          "87s": {
            "call": 0.96
          },
          "76s": {
            "call": 0.94
          },
          "65s": {
            "call": 1
          },
          "54s": {
            "call": 1
          }
        }
      }
    }
  },
  "ev": {
    "vs_3bet": {
      "MP": {
        "vs_CO": {
          "AA": 29.55,
          "KK": 14.85,
          "QQ": 4.04,
          "AKs": 3.55,
          "AKo": 1.59,
          "JJ": 0.55,
          "AQs": 0.53,
          "33": 0.33,
          "KJs": 0.22,
          "44": 0.16,
          "AJs": 0.13,
          "87s": 0.11,
          "54s": 0.11,
          "65s": 0.06,
          "KTs": 0.04,
          "98s": 0.03,
          "76s": 0.03,
          "KQs": 0.01,
          "K7s": -0.01
        }
      }
    }
  }
}
